MANIFEST.in
README.rst
setup.cfg
setup.py
zopeskel.txt
docs/HISTORY.rst
pmr2/__init__.py
pmr2.captcha.egg-info/PKG-INFO
pmr2.captcha.egg-info/SOURCES.txt
pmr2.captcha.egg-info/dependency_links.txt
pmr2.captcha.egg-info/entry_points.txt
pmr2.captcha.egg-info/namespace_packages.txt
pmr2.captcha.egg-info/not-zip-safe
pmr2.captcha.egg-info/paster_plugins.txt
pmr2.captcha.egg-info/requires.txt
pmr2.captcha.egg-info/top_level.txt
pmr2/captcha/__init__.py
pmr2/captcha/configure.zcml
pmr2/captcha/interfaces.py
pmr2/captcha/profiles.zcml
pmr2/captcha/browser/__init__.py
pmr2/captcha/browser/configure.zcml
pmr2/captcha/browser/register.py
pmr2/captcha/browser/register.txt
pmr2/captcha/browser/register_form.pt
pmr2/captcha/profiles/default/browserlayer.xml
pmr2/captcha/tests/__init__.py
pmr2/captcha/tests/base.py
pmr2/captcha/tests/test.zcml
pmr2/captcha/tests/test_doctest.py
pmr2/captcha/tests/test_setup.py
pmr2/captcha/tests/view.py