Metadata-Version: 1.0
Name: pmr2.captcha
Version: 0.1
Summary: Adds support for captcha into PMR2.
Home-page: UNKNOWN
Author: Tommy Yu
Author-email: tommy.yu@auckland.ac.nz
License: GPL
Platform: UNKNOWN
Classifier: Programming Language :: Python
Classifier: Topic :: Software Development :: Libraries :: Python Modules
